<?xml version="1.0" encoding="utf-8"?>
<Defs>
  <PawnKindDef Name="TownsfolkBase" Abstract="True">
    <race>Human</race>
    <defaultFactionType>ROM_Townsfolk</defaultFactionType>
    <baseRecruitDifficulty>0.60</baseRecruitDifficulty>
    <chemicalAddictionChance>0.025</chemicalAddictionChance>
    <invNutrition>2.55</invNutrition>
    <itemQuality>Normal</itemQuality>
    <backstoryCryptosleepCommonality>0</backstoryCryptosleepCommonality>
    <maxGenerationAge>75</maxGenerationAge>
  </PawnKindDef>
  <PawnKindDef Name="TownsfolkVillager" ParentName="TownsfolkBase">
    <defName>ROM_TownsfolkVillager</defName>
    <label>villager</label>
    <race>Human</race>
    <combatPower>48</combatPower>
    <itemQuality>Poor</itemQuality>
    <isFighter>false</isFighter>
    <gearHealthRange>
      <min>0.2</min>
      <max>2.0</max>
    </gearHealthRange>
    <apparelTags>
      <li>IndustrialBasic</li>
      <li>IndustrialAdvanced</li>
      <li>CallOfCthulhu_Townsfolk</li>
    </apparelTags>
    <apparelMoney>
      <min>1000</min>
      <max>2000</max>
    </apparelMoney>
    <apparelRequired>
      <li>ROM_Apparel_CallOfCthulhuBowler</li>
    </apparelRequired>
    <apparelAllowHeadgearChance>1.0</apparelAllowHeadgearChance>
    <weaponMoney>
      <min>250</min>
      <max>650</max>
    </weaponMoney>
    <weaponTags>
      <li>CallOfCthulhu_Melee</li>
      <li>CallOfCthulhu_CoastalMelee</li>
    </weaponTags>
    <techHediffsMoney>
      <min>200</min>
      <max>300</max>
    </techHediffsMoney>
    <techHediffsTags>
      <li>Simple</li>
    </techHediffsTags>
    <techHediffsChance>0.001</techHediffsChance>
    <invNutrition>2.55</invNutrition>
    <inventoryOptions>
      <skipChance>0.75</skipChance>
      <subOptionsChooseOne>
        <li>
          <choiceChance>90</choiceChance>
          <thingDef>Silver</thingDef>
          <countRange>
            <min>25</min>
            <max>70</max>
          </countRange>
        </li>
        <li>
          <choiceChance>10</choiceChance>
          <thingDef>Silver</thingDef>
          <countRange>
            <min>700</min>
            <max>1000</max>
          </countRange>
        </li>
      </subOptionsChooseOne>
    </inventoryOptions>
  </PawnKindDef>
  <PawnKindDef ParentName="TownsfolkBase">
    <defName>ROM_TownsfolkMayor</defName>
    <label>town mayor</label>
    <factionLeader>true</factionLeader>
    <race>Human</race>
    <combatPower>48</combatPower>
    <itemQuality>Poor</itemQuality>
    <isFighter>false</isFighter>
    <gearHealthRange>
      <min>0.2</min>
      <max>2.0</max>
    </gearHealthRange>
    <apparelTags>
      <li>IndustrialBasic</li>
      <li>IndustrialAdvanced</li>
      <li>CallOfCthulhu_Townsfolk</li>
    </apparelTags>
    <apparelMoney>
      <min>1000</min>
      <max>2000</max>
    </apparelMoney>
    <apparelAllowHeadgearChance>1.0</apparelAllowHeadgearChance>
    <weaponMoney>
      <min>250</min>
      <max>650</max>
    </weaponMoney>
    <weaponTags>
      <li>CallOfCthulhu_Melee</li>
      <li>CallOfCthulhu_CoastalMelee</li>
    </weaponTags>
    <techHediffsMoney>
      <min>200</min>
      <max>300</max>
    </techHediffsMoney>
    <techHediffsTags>
      <li>Simple</li>
    </techHediffsTags>
    <techHediffsChance>0.001</techHediffsChance>
    <invNutrition>2.55</invNutrition>
    <inventoryOptions>
      <skipChance>0.75</skipChance>
      <subOptionsChooseOne>
        <li>
          <choiceChance>90</choiceChance>
          <thingDef>Silver</thingDef>
          <countRange>
            <min>25</min>
            <max>70</max>
          </countRange>
        </li>
        <li>
          <choiceChance>10</choiceChance>
          <thingDef>Silver</thingDef>
          <countRange>
            <min>700</min>
            <max>1000</max>
          </countRange>
        </li>
      </subOptionsChooseOne>
    </inventoryOptions>
  </PawnKindDef>
  <PawnKindDef ParentName="TownsfolkVillager">
    <defName>ROM_TownsfolkTrader</defName>
    <label>town trader</label>
    <trader>true</trader>
  </PawnKindDef>
</Defs>